lib/__init__.py
lib/main.py
SMAdiffz-1.1.1.dist-info/LICENSE.txt
SMAdiffz-1.1.1.dist-info/METADATA
SMAdiffz-1.1.1.dist-info/WHEEL
SMAdiffz-1.1.1.dist-info/top_level.txt
SMAdiffz-1.1.1.dist-info/RECORD
