Metadata-Version: 2.1
Name: SMAdiffz
Version: 1.1.1
Summary: Powerful data structures for data analysis, time series for information diffusion analysis
Author: H.M.M.Caldera
Author-email: <maneeshac2020@gmail.com>
Keywords: python,social media
Classifier: Development Status :: 1 - Planning
Classifier: Intended Audience :: Developers
Classifier: Programming Language :: Python :: 3
Classifier: Operating System :: Unix
Classifier: Operating System :: MacOS :: MacOS X
Classifier: Operating System :: Microsoft :: Windows
License-File: LICENSE.txt
Requires-Dist: pandas
Requires-Dist: numpy
